{
  "annotations": {
    "changelogDate": "20250104130022"
  },
  "applications": "*",
  "fields": [
    {
      "fieldName": "name",
      "fieldType": "String"
    },
    {
      "fieldName": "description",
      "fieldType": "String"
    },
    {
      "fieldName": "vendor",
      "fieldType": "String"
    },
    {
      "fieldName": "linkUrl",
      "fieldType": "String"
    },
    {
      "fieldName": "isActive",
      "fieldType": "Boolean"
    },
    {
      "fieldName": "createdBy",
      "fieldType": "String"
    },
    {
      "fieldName": "createdOn",
      "fieldType": "LocalDate"
    },
    {
      "fieldName": "updatedBy",
      "fieldType": "String"
    },
    {
      "fieldName": "updatedOn",
      "fieldType": "LocalDate"
    }
  ],
  "name": "AiTool",
  "relationships": [
    {
      "otherEntityName": "aiToolSession",
      "otherEntityRelationshipName": "tool",
      "relationshipName": "aiSessions",
      "relationshipSide": "left",
      "relationshipType": "one-to-many"
    }
  ],
  "searchEngine": "no"
}
